setup.py
tomproxies/main.py
tomproxies.egg-info/PKG-INFO
tomproxies.egg-info/SOURCES.txt
tomproxies.egg-info/dependency_links.txt
tomproxies.egg-info/top_level.txt