Metadata-Version: 1.1
Name: tomproxies
Version: 1.0
Summary: premium proxies
Home-page: UNKNOWN
Author: bluesatan
Author-email: UNKNOWN
License: MIT
Keywords: style
Platform: UNKNOWN
Classifier: Development Status :: 5 - Production/Stable
